README.md
setup.py
./DFReader.py
./__init__.py
./fgFDM.py
./mavexpression.py
./mavextra.py
./mavparm.py
./mavutil.py
./mavwp.py
./quaternion.py
./rotmat.py
./dialects/__init__.py
./dialects/v10/ASLUAV.py
./dialects/v10/ASLUAV.xml
./dialects/v10/__init__.py
./dialects/v10/ardupilotmega.py
./dialects/v10/ardupilotmega.xml
./dialects/v10/autoquad.py
./dialects/v10/autoquad.xml
./dialects/v10/common.py
./dialects/v10/common.xml
./dialects/v10/icarous.py
./dialects/v10/icarous.xml
./dialects/v10/matrixpilot.py
./dialects/v10/matrixpilot.xml
./dialects/v10/minimal.py
./dialects/v10/minimal.xml
./dialects/v10/paparazzi.py
./dialects/v10/paparazzi.xml
./dialects/v10/python_array_test.py
./dialects/v10/python_array_test.xml
./dialects/v10/slugs.py
./dialects/v10/slugs.xml
./dialects/v10/standard.py
./dialects/v10/standard.xml
./dialects/v10/test.py
./dialects/v10/test.xml
./dialects/v10/uAvionix.py
./dialects/v10/uAvionix.xml
./dialects/v10/ualberta.py
./dialects/v10/ualberta.xml
./dialects/v20/ASLUAV.py
./dialects/v20/ASLUAV.xml
./dialects/v20/__init__.py
./dialects/v20/ardupilotmega.py
./dialects/v20/ardupilotmega.xml
./dialects/v20/autoquad.py
./dialects/v20/autoquad.xml
./dialects/v20/common.py
./dialects/v20/common.xml
./dialects/v20/icarous.py
./dialects/v20/icarous.xml
./dialects/v20/matrixpilot.py
./dialects/v20/matrixpilot.xml
./dialects/v20/minimal.py
./dialects/v20/minimal.xml
./dialects/v20/paparazzi.py
./dialects/v20/paparazzi.xml
./dialects/v20/python_array_test.py
./dialects/v20/python_array_test.xml
./dialects/v20/slugs.py
./dialects/v20/slugs.xml
./dialects/v20/standard.py
./dialects/v20/standard.xml
./dialects/v20/test.py
./dialects/v20/test.xml
./dialects/v20/uAvionix.py
./dialects/v20/uAvionix.xml
./dialects/v20/ualberta.py
./dialects/v20/ualberta.xml
./generator/__init__.py
./generator/mavcrc.py
./generator/mavgen.py
./generator/mavgen_c.py
./generator/mavgen_cpp11.py
./generator/mavgen_cs.py
./generator/mavgen_java.py
./generator/mavgen_javascript.py
pymavlink_ws.egg-info/PKG-INFO
pymavlink_ws.egg-info/SOURCES.txt
pymavlink_ws.egg-info/dependency_links.txt
pymavlink_ws.egg-info/requires.txt
pymavlink_ws.egg-info/top_level.txt
